{
    "matrix": {},
    "pflichten": [],
    "feedback": [
        {
            "datum": "19:17:08",
            "nachricht": "heute war f\u00fcr mich ein wunderbarer tag mit euch<3"
        },
        {
            "datum": "2026-04-27 20:03:29.584612",
            "msg": "Heute war ein wundersch\u00f6ner Tag danke an alle<3"
        },
        {
            "datum": "2026-04-27 20:47:07.491530",
            "msg": "Danke <3"
        },
        {
            "datum": "2026-04-27 21:05:37.909547",
            "msg": "Test <3"
        },
        {
            "datum": "2026-04-27 21:14:10.940104",
            "msg": "Test bug gefixt?Genius das war echt hamma mit dir zusammen<3"
        },
        {
            "datum": "2026-04-27 21:14:47.457513",
            "msg": "Test bug gefixt?Genius das war echt hamma mit dir zusammen<3"
        },
        {
            "datum": "2026-04-28 10:15:03.952310",
            "msg": "juhu wir sind on lieber Genius GZ!"
        }
    ],
    "user_config": [
        "Papa",
        "Lea",
        "Nele",
        "Rapipat"
    ]
}